sincpro_framework/__init__.py
sincpro_framework/bus.py
sincpro_framework/bus.pyi
sincpro_framework/conf/sincpro_framework_conf.yml
sincpro_framework/context/__init__.py
sincpro_framework/context/framework_context.py
sincpro_framework/context/framework_context.pyi
sincpro_framework/context/mixin.py
sincpro_framework/ddd/__init__.py
sincpro_framework/ddd/value_object.py
sincpro_framework/exceptions.py
sincpro_framework/generate_documentation/__init__.py
sincpro_framework/generate_documentation/domain/__init__.py
sincpro_framework/generate_documentation/domain/extractor.py
sincpro_framework/generate_documentation/domain/models.py
sincpro_framework/generate_documentation/infrastructure/__init__.py
sincpro_framework/generate_documentation/infrastructure/framework_docs_extractor.py
sincpro_framework/generate_documentation/infrastructure/json_schema_generator.py
sincpro_framework/generate_documentation/infrastructure/mkdocs_markdown_generator.py
sincpro_framework/generate_documentation/infrastructure/mkdocs_yaml_generator.py
sincpro_framework/generate_documentation/infrastructure/sincpro_introspector.py
sincpro_framework/generate_documentation/infrastructure/static_site_generator.py
sincpro_framework/generate_documentation/service.py
sincpro_framework/generate_documentation/sincpro_framework_ai_guide.json
sincpro_framework/ioc.py
sincpro_framework/middleware.py
sincpro_framework/py.typed
sincpro_framework/sincpro_abstractions.py
sincpro_framework/sincpro_abstractions.pyi
sincpro_framework/sincpro_conf.py
sincpro_framework/sincpro_logger.py
sincpro_framework/use_bus.py
sincpro_framework/use_bus.pyi
sincpro_framework-3.0.6.dist-info/METADATA
sincpro_framework-3.0.6.dist-info/WHEEL
sincpro_framework-3.0.6.dist-info/licenses/LICENSE.md
sincpro_framework-3.0.6.dist-info/RECORD
