Metadata-Version: 2.4
Name: sincpro-framework
Version: 3.0.6
Summary: Sincpro framework to use DDD, Clean architecture, Hexagonal architecture
License: MIT
License-File: LICENSE.md
Author: Gutierrez Andres
Author-email: andru1236@gmail.com
Requires-Python: >=3.12,<4.0
Classifier: License :: OSI Approved :: MIT License
Classifier: Programming Language :: Python :: 3
Classifier: Programming Language :: Python :: 3.12
Classifier: Programming Language :: Python :: 3.13
Classifier: Programming Language :: Python :: 3.14
Requires-Dist: dependency-injector (>=4.48.3,<5.0.0)
Requires-Dist: pydantic (>=2.12.5,<3.0.0)
Requires-Dist: pyyaml (==6.0.1)
Requires-Dist: sincpro-log (>=1.0.1,<2.0.0)
